edgar_analysis/__init__.py
edgar_analysis/main.py
edgar_analysis/examples/__init__.py
edgar_analysis/examples/plot_revenues.py
edgar_analysis/financial_statements/__init__.py
edgar_analysis/financial_statements/accounting_items_config.py
edgar_analysis/financial_statements/balance_sheet.py
edgar_analysis/financial_statements/cashflow_statement.py
edgar_analysis/financial_statements/income_statement.py
edgar_analysis/utils/__init__.py
edgar_analysis/utils/data_calculation.py
edgar_analysis/utils/data_extractor.py
edgar_analysis/utils/synonyms.py
edgar_analysis/utils/tools.py
edgar_analysis/utils/yahoo_finance_data.py
edgar_analysis-0.1.1.dist-info/licenses/LICENSE.txt
edgar_analysis-0.1.1.dist-info/METADATA
edgar_analysis-0.1.1.dist-info/WHEEL
edgar_analysis-0.1.1.dist-info/top_level.txt
edgar_analysis-0.1.1.dist-info/RECORD
