Metadata-Version: 2.4
Name: edgar_analysis
Version: 0.1.1
Summary: A package for analyzing EDGAR financial statements for companies
Home-page: https://github.com/gafzan/edgar_analysis
Author: Jonas Bergstrom
Author-email: gafzan@gmail.com
Classifier: Programming Language :: Python :: 3
Classifier: License :: OSI Approved :: MIT License
Classifier: Operating System :: OS Independent
Requires-Python: >=3.8
License-File: LICENSE.txt
Requires-Dist: pandas
Requires-Dist: numpy
Requires-Dist: dateparser==1.2.2
Requires-Dist: edgartools==4.3.1
Requires-Dist: yfinance==0.2.64
Requires-Dist: tqdm<5.0,>=4.0
Requires-Dist: pydantic==2.11.7
Requires-Dist: matplotlib
Requires-Dist: setuptools
Requires-Dist: twine
Requires-Dist: packaging
Dynamic: author-email
Dynamic: classifier
Dynamic: description
Dynamic: description-content-type
Dynamic: home-page
Dynamic: license-file
Dynamic: requires-dist
Dynamic: requires-python
Dynamic: summary
